[
  {
    "name": "app",
    "image": "${app_image}",
    "essential": true,
    "memoryReservation": 256,
    "environment": [
      { "name": "SECRET_KEY", "value": "${SECRET_KEY}" },
      { "name": "POSTGRES_HOST", "value": "${POSTGRES_HOST}" },
      { "name": "POSTGRES_NAME", "value": "${POSTGRES_NAME}" },
      { "name": "POSTGRES_USER", "value": "${POSTGRES_USER}" },
      { "name": "POSTGRES_PASSWORD", "value": "${POSTGRES_PASSWORD}" },
      { "name": "ALLOWED_HOSTS", "value": "${ALLOWED_HOSTS}" }
    ],
    "logConfiguration": {
      "logDriver": "awslogs",
      "options": {
        "awslogs-group": "${log_group_name}",
        "awslogs-region": "${log_group_region}",
        "awslogs-stream-prefix": "app"
      }
    },
    "portMappings": [
      {
        "containerPort": 8000,
        "hostPort": 8000
      }
    ],
    "mountPoints": [
      {
        "readOnly": false,
        "containerPath": "/code/static",
        "sourceVolume": "static"
      }
    ]
  },
  {
    "name": "web",
    "image": "${nginx_image}",
    "essential": true,
    "portMappings": [
      {
        "containerPort": 80,
        "hostPort": 80
      }
    ],
    "memoryReservation": 256,
    "environment": [
      { "name": "APP_HOST", "value": "127.0.0.1" },
      { "name": "APP_PORT", "value": "8000" },
      { "name": "LISTEN_PORT", "value": "80" }
    ],
    "logConfiguration": {
      "logDriver": "awslogs",
      "options": {
        "awslogs-group": "${log_group_name}",
        "awslogs-region": "${log_group_region}",
        "awslogs-stream-prefix": "proxy"
      }
    },
    "mountPoints": [
      {
        "readOnly": true,
        "containerPath": "/code/static",
        "sourceVolume": "static"
      }
    ]
  }
]
